osu_apy_v2/__init__.py
osu_apy_v2/api.py
osu_apy_v2/database.py
osu_apy_v2/exceptions.py
osu_apy_v2-0.1.7.dist-info/LICENSE
osu_apy_v2-0.1.7.dist-info/WHEEL
osu_apy_v2-0.1.7.dist-info/METADATA
osu_apy_v2-0.1.7.dist-info/RECORD
