Metadata-Version: 2.1
Name: osu-apy-v2
Version: 0.1.7
Summary: small osu api v2 helper
Home-page: https://gitlab.com/Eulentier161/osu_apy_v2
Author: Eulentier161
Author-email: eulentier161@gmail.com
Requires-Python: >=3.8,<4.0
Classifier: Programming Language :: Python :: 3
Classifier: Programming Language :: Python :: 3.10
Classifier: Programming Language :: Python :: 3.8
Classifier: Programming Language :: Python :: 3.9
Requires-Dist: pyaml (>=21.10.1,<22.0.0)
Requires-Dist: requests (>=2.28.0,<3.0.0)
Project-URL: Repository, https://gitlab.com/Eulentier161/osu_apy_v2
